cat/__init__.py
cat/base.py
cat/env.py
cat/log.py
cat/main.py
cat/paths.py
cat/startup.py
cat/urls.py
cat/utils.py
cat/welcome.txt
cat/auth/__init__.py
cat/auth/connection.py
cat/auth/permissions.py
cat/auth/user.py
cat/db/__init__.py
cat/db/database.py
cat/db/helper.py
cat/db/models.py
cat/looking_glass/cheshire_cat.py
cat/looking_glass/hook_context.py
cat/looking_glass/prompts.py
cat/looking_glass/stray_cat.py
cat/mad_hatter/mad_hatter.py
cat/mad_hatter/plugin.py
cat/mad_hatter/plugin_extractor.py
cat/mad_hatter/plugin_manifest.py
cat/mad_hatter/registry.py
cat/mad_hatter/decorators/__init__.py
cat/mad_hatter/decorators/endpoint.py
cat/mad_hatter/decorators/hook.py
cat/mad_hatter/decorators/plugin_decorator.py
cat/mad_hatter/decorators/tool.py
cat/mixin/llm.py
cat/mixin/stream.py
cat/protocols/agui/__init__.py
cat/protocols/agui/streaming.py
cat/protocols/future/embedder.py
cat/protocols/future/llm.py
cat/protocols/future/llm_callbacks.py
cat/protocols/future/llm_wrapper.py
cat/protocols/model_context/client.py
cat/protocols/model_context/server.py
cat/protocols/model_context/type_wrappers.py
cat/routes/__init__.py
cat/routes/home.py
cat/routes/openapi.py
cat/routes/services.py
cat/routes/status.py
cat/routes/uploads.py
cat/routes/auth/oauth.py
cat/routes/auth/default_idp/idp.html
cat/routes/auth/default_idp/idp.py
cat/routes/common/crud.py
cat/routes/common/schemas.py
cat/routes/mcp/registry.py
cat/routes/me/me.py
cat/routes/me/settings.py
cat/routes/plugins/plugins.py
cat/routes/plugins/plugins_local.py
cat/routes/plugins/plugins_registry.py
cat/routes/plugins/plugins_settings.py
cat/routes/websocket/websocket.py
cat/scaffold/scaffolder.py
cat/scaffold/data/readme.md
cat/scaffold/data/uploads/readme.md
cat/scaffold/plugins/readme.md
cat/services/__factory.py
cat/services/factory.py
cat/services/service.py
cat/services/agents/base.py
cat/services/agents/default.py
cat/services/auths/base.py
cat/services/auths/default.py
cat/services/directives/base.py
cheshire_cat_ai-2.0.12.dist-info/METADATA
cheshire_cat_ai-2.0.12.dist-info/WHEEL
cheshire_cat_ai-2.0.12.dist-info/entry_points.txt
cheshire_cat_ai-2.0.12.dist-info/licenses/LICENSE
cheshire_cat_ai-2.0.12.dist-info/RECORD
