Metadata-Version: 2.4
Name: cheshire-cat-ai
Version: 2.0.12
Summary: Production ready AI agent framework
Project-URL: Homepage, https://github.com/cheshire-cat-ai/core
Project-URL: Issues, https://github.com/cheshire-cat-ai/core/issues
Author: Piero Savastano, Cheshire Cat AI Contributors
License-Expression: GPL-3.0
License-File: LICENSE
Requires-Python: >=3.13
Requires-Dist: ag-ui-protocol>=0.1.8
Requires-Dist: aiofiles>=24.1.0
Requires-Dist: asgi-lifespan>=2.1.0
Requires-Dist: bcrypt>=4.1.3
Requires-Dist: cachetools>=6.2.0
Requires-Dist: debugpy>=1.8.16
Requires-Dist: fastapi[standard]>=0.121.0
Requires-Dist: fastmcp>=2.12.4
Requires-Dist: httpx>=0.28.1
Requires-Dist: langchain-core>=1.1.0
Requires-Dist: loguru>=0.7.2
Requires-Dist: piccolo[all]>=1.30.0
Requires-Dist: pillow>=11.3.0
Requires-Dist: punq>=0.7.0
Requires-Dist: pydantic>=2.12.4
Requires-Dist: pyjwt>=2.8.0
Requires-Dist: pytest
Requires-Dist: pytest-asyncio
Requires-Dist: python-slugify>=8.0.1
Requires-Dist: pytz>=2025.2
Requires-Dist: rapidfuzz>=3.6.1
Requires-Dist: ruff>=0.4.7
Requires-Dist: scalar-fastapi>=1.4.3
Requires-Dist: uvicorn[standard]>=0.38.0
Requires-Dist: websockets>=15.0
